classyclient
